napalm_exaros/__init__.py
napalm_exaros/exaros.py
napalm_exaros/ssh.py
napalm_exaros/utils/__init__.py
napalm_exaros-0.1.0.dist-info/DESCRIPTION.rst
napalm_exaros-0.1.0.dist-info/METADATA
napalm_exaros-0.1.0.dist-info/RECORD
napalm_exaros-0.1.0.dist-info/WHEEL
napalm_exaros-0.1.0.dist-info/metadata.json
napalm_exaros-0.1.0.dist-info/top_level.txt
