Metadata-Version: 2.0
Name: napalm-exaros
Version: 0.1.0
Summary: Network Automation and Programmability Abstraction Layer with     Multivendor support
Home-page: https://github.com/wolcomm/napalm-exaros
Author: Ben Maddison
Author-email: benm@workonline.co.za
License: UNKNOWN
Platform: UNKNOWN
Classifier: Topic :: Utilities
Classifier: Programming Language :: Python
Classifier: Programming Language :: Python :: 2
Classifier: Programming Language :: Python :: 2.7
Classifier: Operating System :: POSIX :: Linux
Classifier: Operating System :: MacOS
Requires-Dist: napalm-base (>=0.24.0)
Requires-Dist: netmiko (>=1.4.1)
